bei/beipack.py.template
bei/pack.py
beipack-0.dist-info/METADATA
beipack-0.dist-info/WHEEL
beipack-0.dist-info/entry_points.txt
beipack-0.dist-info/top_level.txt
beipack-0.dist-info/RECORD
