Metadata-Version: 2.1
Name: beipack
Version: 0
Summary: beipack
Author-email: Allison Karlitskaya <allison.karlitskaya@redhat.com>
Project-URL: Home, https://github.com/allisonkarlitskaya/beipack/
Classifier: License :: OSI Approved :: GNU General Public License v3 or later (GPLv3+)
